MergeGoogleDocWithIpynb/CodeResourceAnalyzer.py
MergeGoogleDocWithIpynb/Exception.py
MergeGoogleDocWithIpynb/MarkdownResourceAnalyzer.py
MergeGoogleDocWithIpynb/MergeToIpynb.py
MergeGoogleDocWithIpynb/ResourceAnalyzer.py
MergeGoogleDocWithIpynb/ResourceCollector.py
MergeGoogleDocWithIpynb/Types.py
MergeGoogleDocWithIpynb/Utility.py
MergeGoogleDocWithIpynb/__init__.py
tests/__init__.py
tests/test_CodeResourceContainer.py
tests/test_MdResourceContainer.py
tests/test_MergeToIpynb.py
tests/test_ResourceCollector.py
tests/test_Utility.py
mergegoogledocwithipynb-0.2.1.dist-info/LICENSE
mergegoogledocwithipynb-0.2.1.dist-info/METADATA
mergegoogledocwithipynb-0.2.1.dist-info/WHEEL
mergegoogledocwithipynb-0.2.1.dist-info/top_level.txt
mergegoogledocwithipynb-0.2.1.dist-info/RECORD
